{"id":"node_modules/rxjs-compat/operator/mergeMapTo.js","dependencies":[{"name":"/Users/ben/Documents/w/myproject/learn/rxjs/node_modules/rxjs-compat/package.json","includedInParent":true,"mtime":499162500000},{"name":"/Users/ben/Documents/w/myproject/learn/rxjs/package.json","includedInParent":true,"mtime":1531619120174},{"name":"rxjs/operators","loc":{"line":3,"column":26},"parent":"/Users/ben/Documents/w/myproject/learn/rxjs/node_modules/rxjs-compat/operator/mergeMapTo.js","resolved":"/Users/ben/Documents/w/myproject/learn/rxjs/node_modules/rxjs/_esm5/operators/index.js"}],"generated":{"js":"\"use strict\";\nObject.defineProperty(exports, \"__esModule\", { value: true });\nvar operators_1 = require(\"rxjs/operators\");\n/**\n * Projects each source value to the same Observable which is merged multiple\n * times in the output Observable.\n *\n * <span class=\"informal\">It's like {@link mergeMap}, but maps each value always\n * to the same inner Observable.</span>\n *\n * <img src=\"./img/mergeMapTo.png\" width=\"100%\">\n *\n * Maps each source value to the given Observable `innerObservable` regardless\n * of the source value, and then merges those resulting Observables into one\n * single Observable, which is the output Observable.\n *\n * @example <caption>For each click event, start an interval Observable ticking every 1 second</caption>\n * var clicks = Rx.Observable.fromEvent(document, 'click');\n * var result = clicks.mergeMapTo(Rx.Observable.interval(1000));\n * result.subscribe(x => console.log(x));\n *\n * @see {@link concatMapTo}\n * @see {@link merge}\n * @see {@link mergeAll}\n * @see {@link mergeMap}\n * @see {@link mergeScan}\n * @see {@link switchMapTo}\n *\n * @param {ObservableInput} innerObservable An Observable to replace each value from\n * the source Observable.\n * @param {number} [concurrent=Number.POSITIVE_INFINITY] Maximum number of input\n * Observables being subscribed to concurrently.\n * @return {Observable} An Observable that emits items from the given\n * `innerObservable`.\n * @method mergeMapTo\n * @owner Observable\n */\nfunction mergeMapTo(innerObservable, concurrent) {\n    if (concurrent === void 0) { concurrent = Number.POSITIVE_INFINITY; }\n    return operators_1.mergeMapTo(innerObservable, concurrent)(this);\n}\nexports.mergeMapTo = mergeMapTo;\n//# sourceMappingURL=mergeMapTo.js.map","map":{"mappings":[{"source":"node_modules/rxjs-compat/operator/mergeMapTo.js","original":{"line":1,"column":0},"generated":{"line":1,"column":0}},{"source":"node_modules/rxjs-compat/operator/mergeMapTo.js","original":{"line":2,"column":0},"generated":{"line":2,"column":0}},{"source":"node_modules/rxjs-compat/operator/mergeMapTo.js","original":{"line":3,"column":0},"generated":{"line":3,"column":0}},{"source":"node_modules/rxjs-compat/operator/mergeMapTo.js","original":{"line":4,"column":0},"generated":{"line":4,"column":0}},{"source":"node_modules/rxjs-compat/operator/mergeMapTo.js","original":{"line":5,"column":0},"generated":{"line":5,"column":0}},{"source":"node_modules/rxjs-compat/operator/mergeMapTo.js","original":{"line":6,"column":0},"generated":{"line":6,"column":0}},{"source":"node_modules/rxjs-compat/operator/mergeMapTo.js","original":{"line":7,"column":0},"generated":{"line":7,"column":0}},{"source":"node_modules/rxjs-compat/operator/mergeMapTo.js","original":{"line":8,"column":0},"generated":{"line":8,"column":0}},{"source":"node_modules/rxjs-compat/operator/mergeMapTo.js","original":{"line":9,"column":0},"generated":{"line":9,"column":0}},{"source":"node_modules/rxjs-compat/operator/mergeMapTo.js","original":{"line":10,"column":0},"generated":{"line":10,"column":0}},{"source":"node_modules/rxjs-compat/operator/mergeMapTo.js","original":{"line":11,"column":0},"generated":{"line":11,"column":0}},{"source":"node_modules/rxjs-compat/operator/mergeMapTo.js","original":{"line":12,"column":0},"generated":{"line":12,"column":0}},{"source":"node_modules/rxjs-compat/operator/mergeMapTo.js","original":{"line":13,"column":0},"generated":{"line":13,"column":0}},{"source":"node_modules/rxjs-compat/operator/mergeMapTo.js","original":{"line":14,"column":0},"generated":{"line":14,"column":0}},{"source":"node_modules/rxjs-compat/operator/mergeMapTo.js","original":{"line":15,"column":0},"generated":{"line":15,"column":0}},{"source":"node_modules/rxjs-compat/operator/mergeMapTo.js","original":{"line":16,"column":0},"generated":{"line":16,"column":0}},{"source":"node_modules/rxjs-compat/operator/mergeMapTo.js","original":{"line":17,"column":0},"generated":{"line":17,"column":0}},{"source":"node_modules/rxjs-compat/operator/mergeMapTo.js","original":{"line":18,"column":0},"generated":{"line":18,"column":0}},{"source":"node_modules/rxjs-compat/operator/mergeMapTo.js","original":{"line":19,"column":0},"generated":{"line":19,"column":0}},{"source":"node_modules/rxjs-compat/operator/mergeMapTo.js","original":{"line":20,"column":0},"generated":{"line":20,"column":0}},{"source":"node_modules/rxjs-compat/operator/mergeMapTo.js","original":{"line":21,"column":0},"generated":{"line":21,"column":0}},{"source":"node_modules/rxjs-compat/operator/mergeMapTo.js","original":{"line":22,"column":0},"generated":{"line":22,"column":0}},{"source":"node_modules/rxjs-compat/operator/mergeMapTo.js","original":{"line":23,"column":0},"generated":{"line":23,"column":0}},{"source":"node_modules/rxjs-compat/operator/mergeMapTo.js","original":{"line":24,"column":0},"generated":{"line":24,"column":0}},{"source":"node_modules/rxjs-compat/operator/mergeMapTo.js","original":{"line":25,"column":0},"generated":{"line":25,"column":0}},{"source":"node_modules/rxjs-compat/operator/mergeMapTo.js","original":{"line":26,"column":0},"generated":{"line":26,"column":0}},{"source":"node_modules/rxjs-compat/operator/mergeMapTo.js","original":{"line":27,"column":0},"generated":{"line":27,"column":0}},{"source":"node_modules/rxjs-compat/operator/mergeMapTo.js","original":{"line":28,"column":0},"generated":{"line":28,"column":0}},{"source":"node_modules/rxjs-compat/operator/mergeMapTo.js","original":{"line":29,"column":0},"generated":{"line":29,"column":0}},{"source":"node_modules/rxjs-compat/operator/mergeMapTo.js","original":{"line":30,"column":0},"generated":{"line":30,"column":0}},{"source":"node_modules/rxjs-compat/operator/mergeMapTo.js","original":{"line":31,"column":0},"generated":{"line":31,"column":0}},{"source":"node_modules/rxjs-compat/operator/mergeMapTo.js","original":{"line":32,"column":0},"generated":{"line":32,"column":0}},{"source":"node_modules/rxjs-compat/operator/mergeMapTo.js","original":{"line":33,"column":0},"generated":{"line":33,"column":0}},{"source":"node_modules/rxjs-compat/operator/mergeMapTo.js","original":{"line":34,"column":0},"generated":{"line":34,"column":0}},{"source":"node_modules/rxjs-compat/operator/mergeMapTo.js","original":{"line":35,"column":0},"generated":{"line":35,"column":0}},{"source":"node_modules/rxjs-compat/operator/mergeMapTo.js","original":{"line":36,"column":0},"generated":{"line":36,"column":0}},{"source":"node_modules/rxjs-compat/operator/mergeMapTo.js","original":{"line":37,"column":0},"generated":{"line":37,"column":0}},{"source":"node_modules/rxjs-compat/operator/mergeMapTo.js","original":{"line":38,"column":0},"generated":{"line":38,"column":0}},{"source":"node_modules/rxjs-compat/operator/mergeMapTo.js","original":{"line":39,"column":0},"generated":{"line":39,"column":0}},{"source":"node_modules/rxjs-compat/operator/mergeMapTo.js","original":{"line":40,"column":0},"generated":{"line":40,"column":0}},{"source":"node_modules/rxjs-compat/operator/mergeMapTo.js","original":{"line":41,"column":0},"generated":{"line":41,"column":0}},{"source":"node_modules/rxjs-compat/operator/mergeMapTo.js","original":{"line":42,"column":0},"generated":{"line":42,"column":0}},{"source":"node_modules/rxjs-compat/operator/mergeMapTo.js","original":{"line":43,"column":0},"generated":{"line":43,"column":0}}],"sources":{"node_modules/rxjs-compat/operator/mergeMapTo.js":"\"use strict\";\nObject.defineProperty(exports, \"__esModule\", { value: true });\nvar operators_1 = require(\"rxjs/operators\");\n/**\n * Projects each source value to the same Observable which is merged multiple\n * times in the output Observable.\n *\n * <span class=\"informal\">It's like {@link mergeMap}, but maps each value always\n * to the same inner Observable.</span>\n *\n * <img src=\"./img/mergeMapTo.png\" width=\"100%\">\n *\n * Maps each source value to the given Observable `innerObservable` regardless\n * of the source value, and then merges those resulting Observables into one\n * single Observable, which is the output Observable.\n *\n * @example <caption>For each click event, start an interval Observable ticking every 1 second</caption>\n * var clicks = Rx.Observable.fromEvent(document, 'click');\n * var result = clicks.mergeMapTo(Rx.Observable.interval(1000));\n * result.subscribe(x => console.log(x));\n *\n * @see {@link concatMapTo}\n * @see {@link merge}\n * @see {@link mergeAll}\n * @see {@link mergeMap}\n * @see {@link mergeScan}\n * @see {@link switchMapTo}\n *\n * @param {ObservableInput} innerObservable An Observable to replace each value from\n * the source Observable.\n * @param {number} [concurrent=Number.POSITIVE_INFINITY] Maximum number of input\n * Observables being subscribed to concurrently.\n * @return {Observable} An Observable that emits items from the given\n * `innerObservable`.\n * @method mergeMapTo\n * @owner Observable\n */\nfunction mergeMapTo(innerObservable, concurrent) {\n    if (concurrent === void 0) { concurrent = Number.POSITIVE_INFINITY; }\n    return operators_1.mergeMapTo(innerObservable, concurrent)(this);\n}\nexports.mergeMapTo = mergeMapTo;\n//# sourceMappingURL=mergeMapTo.js.map"},"lineCount":43}},"hash":"803771f5d36eff6d26a63261e5fa8adc","cacheData":{"env":{}}}